expirebackups/__init__.py
expirebackups/expire.py
expirebackups/version.py
pyexpirebackups-0.1.1.dist-info/METADATA
pyexpirebackups-0.1.1.dist-info/WHEEL
pyexpirebackups-0.1.1.dist-info/entry_points.txt
pyexpirebackups-0.1.1.dist-info/licenses/LICENSE
pyexpirebackups-0.1.1.dist-info/RECORD
