Metadata-Version: 2.4
Name: pyExpireBackups
Version: 0.1.1
Summary: Automated cleanup and expiration of backup files based on age and retention rules.
Project-URL: Home, https://github.com/WolfgangFahl/pyExpireBackups
Project-URL: Documentation, https://wiki.bitplan.com/index.php/pyExpireBackups
Project-URL: Source, https://github.com/WolfgangFahl/pyExpireBackups
Author-email: Wolfgang Fahl <wf@WolfgangFahl.com>
Maintainer-email: Wolfgang Fahl <wf@WolfgangFahl.com>
License: Apache-2.0
License-File: LICENSE
Keywords: automation,backup,cleanup,retention
Classifier: Development Status :: 4 - Beta
Classifier: Intended Audience :: Developers
Classifier: License :: OSI Approved :: Apache Software License
Classifier: Operating System :: OS Independent
Classifier: Programming Language :: Python :: 3 :: Only
Classifier: Programming Language :: Python :: 3.10
Classifier: Programming Language :: Python :: 3.11
Classifier: Programming Language :: Python :: 3.12
Classifier: Programming Language :: Python :: 3.13
Classifier: Topic :: System :: Archiving :: Backup
Classifier: Topic :: Utilities
Requires-Python: >=3.10
Provides-Extra: dev
Requires-Dist: black>=25.1.0; extra == 'dev'
Requires-Dist: isort>=6.0.1; extra == 'dev'
Provides-Extra: test
Requires-Dist: green>=3.3.0; extra == 'test'
Requires-Dist: pytest>=8.4.0; extra == 'test'
Requires-Dist: tox>=4.15.0; extra == 'test'
